sema4ai/di_client/__init__.py
sema4ai/di_client/_document_intelligence_client_impl.py
sema4ai/di_client/agents_events_publisher/__init__.py
sema4ai/di_client/agents_events_publisher/api/__init__.py
sema4ai/di_client/agents_events_publisher/api/default_api.py
sema4ai/di_client/agents_events_publisher/api_client.py
sema4ai/di_client/agents_events_publisher/api_response.py
sema4ai/di_client/agents_events_publisher/configuration.py
sema4ai/di_client/agents_events_publisher/exceptions.py
sema4ai/di_client/agents_events_publisher/models/__init__.py
sema4ai/di_client/agents_events_publisher/models/api_v1_work_items_complete_stage_post200_response.py
sema4ai/di_client/agents_events_publisher/models/api_v1_work_items_complete_stage_post_request.py
sema4ai/di_client/agents_events_publisher/models/post_work_items_complete_stage200_response.py
sema4ai/di_client/agents_events_publisher/models/post_work_items_complete_stage_request.py
sema4ai/di_client/agents_events_publisher/py.typed
sema4ai/di_client/agents_events_publisher/rest.py
sema4ai/di_client/document_intelligence_client/__init__.py
sema4ai/di_client/document_intelligence_client/api/__init__.py
sema4ai/di_client/document_intelligence_client/api/default_api.py
sema4ai/di_client/document_intelligence_client/api_client.py
sema4ai/di_client/document_intelligence_client/api_response.py
sema4ai/di_client/document_intelligence_client/configuration.py
sema4ai/di_client/document_intelligence_client/exceptions.py
sema4ai/di_client/document_intelligence_client/models/__init__.py
sema4ai/di_client/document_intelligence_client/models/base_document_content.py
sema4ai/di_client/document_intelligence_client/models/computed_document_content.py
sema4ai/di_client/document_intelligence_client/models/content_state.py
sema4ai/di_client/document_intelligence_client/models/doc_type.py
sema4ai/di_client/document_intelligence_client/models/doc_type_tbl_fields_inner.py
sema4ai/di_client/document_intelligence_client/models/document_class.py
sema4ai_di_client-1.0.14.dist-info/LICENSE
sema4ai_di_client-1.0.14.dist-info/METADATA
sema4ai_di_client-1.0.14.dist-info/WHEEL
sema4ai_di_client-1.0.14.dist-info/RECORD
