Metadata-Version: 2.3
Name: sema4ai-di-client
Version: 1.0.14
Summary: Sema4AI Document Intelligence API client
License: Sema4.ai Proprietary (see LICENSE)
Keywords: OpenAPI,OpenAPI-Generator,Document Intelligence API
Author: Sukeesh V.
Author-email: sukeesh@sema4.ai
Requires-Python: >=3.10,<4.0
Classifier: License :: Other/Proprietary License
Classifier: Programming Language :: Python :: 3
Classifier: Programming Language :: Python :: 3.10
Classifier: Programming Language :: Python :: 3.11
Classifier: Programming Language :: Python :: 3.12
Classifier: Programming Language :: Python :: 3.13
Requires-Dist: pandas (>=2.2.2,<3.0.0)
Requires-Dist: pydantic (>=2.8.2,<3.0.0)
Requires-Dist: python-dateutil (>=2.8.2,<3.0.0)
Requires-Dist: sema4ai-actions (>=1.3.8,<2.0.0)
Requires-Dist: typing-extensions (>=4.11.0,<5.0.0)
Requires-Dist: urllib3 (>=2.2.0,<3.0.0)
Project-URL: Repository, https://github.com/Sema4AI/document-intelligence-client
